textum-0.1.2.dist-info/METADATA
textum-0.1.2.dist-info/WHEEL
textum.libs/libgcc_s-0366c7ba.so.1
textum/__init__.py
textum/__init__.pyi
textum/_textum.abi3.so
textum/py.typed
textum-0.1.2.dist-info/RECORD
