Metadata-Version: 2.4
Name: textum
Version: 0.1.2
Classifier: Programming Language :: Python :: 3
Classifier: Programming Language :: Python :: 3.10
Classifier: Programming Language :: Python :: 3.11
Classifier: Programming Language :: Python :: 3.12
Classifier: Programming Language :: Python :: 3.9
Classifier: Programming Language :: Python :: Implementation :: CPython
Classifier: Programming Language :: Rust
Summary: A syntactic patching library with char-level granularity
Keywords: diff,patch,syntax,tree-sitter
Home-Page: https://github.com/lmmx/textum
Author-email: Louis Maddox <louismmx@gmail.com>
License: MIT
Requires-Python: >=3.9
Project-URL: Homepage, https://github.com/lmmx/textum
Project-URL: Repository, https://github.com/lmmx/textum
